tc_circuit/__init__.py
tc_circuit/component_factory_loader.py
tc_circuit/component_info.json
tc_circuit/component_info.py
tc_circuit/component_types.py
tc_circuit/pygame_viewer.py
tc_circuit/tc_circuit.py
tc_circuit/tc_compiler.py
tc_circuit/to_json.py
tc_circuit/to_svg.py
tc_circuit/atlas/1_decoder.png
tc_circuit/atlas/2_decoder.png
tc_circuit/atlas/3_decoder.png
tc_circuit/atlas/Add8.png
tc_circuit/atlas/And.png
tc_circuit/atlas/And3.png
tc_circuit/atlas/Ashr.png
tc_circuit/atlas/Bidirectional1.png
tc_circuit/atlas/Bidirectional16.png
tc_circuit/atlas/Bidirectional64.png
tc_circuit/atlas/Bidirectional8.png
tc_circuit/atlas/BitMemory.png
tc_circuit/atlas/ByteAnd.png
tc_circuit/atlas/ByteConstant.png
tc_circuit/atlas/ByteEqual.png
tc_circuit/atlas/ByteLessI.png
tc_circuit/atlas/ByteLessU.png
tc_circuit/atlas/ByteNand.png
tc_circuit/atlas/ByteNeg.png
tc_circuit/atlas/ByteNor.png
tc_circuit/atlas/ByteNot.png
tc_circuit/atlas/ByteOr.png
tc_circuit/atlas/ByteRol.png
tc_circuit/atlas/ByteRor.png
tc_circuit/atlas/ByteShl.png
tc_circuit/atlas/ByteShr.png
tc_circuit/atlas/ByteXnor.png
tc_circuit/atlas/ByteXor.png
tc_circuit/atlas/Clock.png
tc_circuit/atlas/Console.png
tc_circuit/atlas/Counter.png
tc_circuit/atlas/DelayBuffer.png
tc_circuit/atlas/DivMod8.png
tc_circuit/atlas/DotMatrixDisplay.png
tc_circuit/atlas/Expander16.png
tc_circuit/atlas/Expander32.png
tc_circuit/atlas/FileRom.png
tc_circuit/atlas/FullAdder.png
tc_circuit/atlas/Halt.png
tc_circuit/atlas/Input1.png
tc_circuit/atlas/Input16.png
tc_circuit/atlas/Input1B.png
tc_circuit/atlas/Input1BCode.png
tc_circuit/atlas/Input1BConditions.png
tc_circuit/atlas/Input1Green.png
tc_circuit/atlas/Input1_1B.png
tc_circuit/atlas/Input2.png
tc_circuit/atlas/Input2Green.png
tc_circuit/atlas/Input3.png
tc_circuit/atlas/Input4.png
tc_circuit/atlas/InputQword.png
tc_circuit/atlas/LevelGate.png
tc_circuit/atlas/LevelGateGreen.png
tc_circuit/atlas/LevelGateGreenCheck.png
tc_circuit/atlas/LevelGateYellow.png
tc_circuit-0.5.0.dist-info/entry_points.txt
tc_circuit-0.5.0.dist-info/LICENSE
tc_circuit-0.5.0.dist-info/WHEEL
tc_circuit-0.5.0.dist-info/METADATA
tc_circuit-0.5.0.dist-info/RECORD
